CHANGELOG.md
LICENSE
MANIFEST.in
README.md
requirements.txt
setup.py
ampl_sphinx_theme/.DS_Store
ampl_sphinx_theme/__init__.py
ampl_sphinx_theme/bootstrap_html_translator.py
ampl_sphinx_theme/docs-navbar.html
ampl_sphinx_theme/docs-sidebar.html
ampl_sphinx_theme/footer.html
ampl_sphinx_theme/icon-links.html
ampl_sphinx_theme/layout.html
ampl_sphinx_theme/navbar-logo.html
ampl_sphinx_theme/search-field.html
ampl_sphinx_theme/theme.conf
ampl_sphinx_theme.egg-info/PKG-INFO
ampl_sphinx_theme.egg-info/SOURCES.txt
ampl_sphinx_theme.egg-info/dependency_links.txt
ampl_sphinx_theme.egg-info/entry_points.txt
ampl_sphinx_theme.egg-info/requires.txt
ampl_sphinx_theme.egg-info/top_level.txt
ampl_sphinx_theme/.vscode/settings.json
ampl_sphinx_theme/_templates/.DS_Store
ampl_sphinx_theme/_templates/copyright.html
ampl_sphinx_theme/_templates/edit-this-page.html
ampl_sphinx_theme/_templates/icon-links.html
ampl_sphinx_theme/_templates/last-updated.html
ampl_sphinx_theme/_templates/navbar-icon-links.html
ampl_sphinx_theme/_templates/navbar-logo.html
ampl_sphinx_theme/_templates/navbar-nav.html
ampl_sphinx_theme/_templates/page-toc.html
ampl_sphinx_theme/_templates/prev-next.html
ampl_sphinx_theme/_templates/sidebar-ethical-ads.html
ampl_sphinx_theme/_templates/sidebar-nav-bs.html
ampl_sphinx_theme/_templates/sphinx-version.html
ampl_sphinx_theme/static/.DS_Store
ampl_sphinx_theme/static/webpack-macros.html
ampl_sphinx_theme/static/css/blank.css
ampl_sphinx_theme/static/css/index.ff1ffe594081f20da1ef19478df9384b.css
ampl_sphinx_theme/static/css/theme.css
ampl_sphinx_theme/static/js/index.be7d3bbb2ef33a8344ce.js
ampl_sphinx_theme/static/vendor/fontawesome/5.13.0/LICENSE.txt
ampl_sphinx_theme/static/vendor/fontawesome/5.13.0/css/all.min.css
ampl_sphinx_theme/static/vendor/fontawesome/5.13.0/webfonts/fa-brands-400.eot
ampl_sphinx_theme/static/vendor/fontawesome/5.13.0/webfonts/fa-brands-400.svg
ampl_sphinx_theme/static/vendor/fontawesome/5.13.0/webfonts/fa-brands-400.ttf
ampl_sphinx_theme/static/vendor/fontawesome/5.13.0/webfonts/fa-brands-400.woff
ampl_sphinx_theme/static/vendor/fontawesome/5.13.0/webfonts/fa-brands-400.woff2
ampl_sphinx_theme/static/vendor/fontawesome/5.13.0/webfonts/fa-regular-400.eot
